[{"name":"sql.active_record","payload":{"sql":"SELECT  \"users\".* FROM \"users\"  WHERE \"users\".\"id\" = $1 LIMIT 1","name":"User Load","connection_id":70167020534400,"binds":[[{"name":"id","sql_type":"integer","null":false,"limit":null,"precision":null,"scale":null,"type":"integer","default":null,"primary":true,"coder":null},1]]},"time":"2013-10-23T09:05:03+01:00","transaction_id":"d3c5160d7f1cf4b422d4","end":"2013-10-23T09:05:03+01:00","duration":0.326},{"name":"sql.active_record","payload":{"sql":"SELECT \"recipes\".* FROM \"recipes\" ","name":"Recipe Load","connection_id":70167020534400,"binds":[]},"time":"2013-10-23T09:05:03+01:00","transaction_id":"d3c5160d7f1cf4b422d4","end":"2013-10-23T09:05:03+01:00","duration":0.389},{"name":"sql.active_record","payload":{"sql":"SELECT  \"users\".* FROM \"users\"  WHERE \"users\".\"id\" = 2 LIMIT 1","name":"User Load","connection_id":70167020534400,"binds":[]},"time":"2013-10-23T09:05:03+01:00","transaction_id":"d3c5160d7f1cf4b422d4","end":"2013-10-23T09:05:03+01:00","duration":0.289},{"name":"sql.active_record","payload":{"sql":"SELECT  \"users\".* FROM \"users\"  WHERE \"users\".\"id\" = 3 LIMIT 1","name":"User Load","connection_id":70167020534400,"binds":[]},"time":"2013-10-23T09:05:03+01:00","transaction_id":"d3c5160d7f1cf4b422d4","end":"2013-10-23T09:05:03+01:00","duration":0.162},{"name":"sql.active_record","payload":{"sql":"SELECT  \"users\".* FROM \"users\"  WHERE \"users\".\"id\" = 3 LIMIT 1","binds":[],"name":"CACHE","connection_id":70167020534400},"time":"2013-10-23T09:05:03+01:00","transaction_id":"8d648c68f8dfadd6fa4f","end":"2013-10-23T09:05:03+01:00","duration":0.002},{"name":"render_template.action_view","payload":{"identifier":"/Users/jon/cookbook_authorization_start/app/views/recipes/index.html.haml","layout":"layouts/application"},"time":"2013-10-23T09:05:03+01:00","transaction_id":"8d648c68f8dfadd6fa4f","end":"2013-10-23T09:05:03+01:00","duration":5.962000000000001},{"name":"process_action.action_controller","payload":{"controller":"RecipesController","action":"index","params":{"action":"index","controller":"recipes"},"format":"html","method":"GET","path":"/recipes","status":200,"view_runtime":8.796,"db_runtime":1.168},"time":"2013-10-23T09:05:03+01:00","transaction_id":"8d648c68f8dfadd6fa4f","end":"2013-10-23T09:05:03+01:00","duration":16.215}]